{"v":"5.7.6","fr":30,"ip":0,"op":120,"w":180,"h":140,"nm":"cameraFlash","ddd":0,"assets":[],"layers":[{"ddd":0,"ind":1,"ty":4,"nm":"ray_0_0","sr":1,"ks":{"o":{"a":1,"k":[{"i":{"x":[0.5],"y":[1]},"o":{"x":[0.5],"y":[0]},"t":40,"s":[0]},{"i":{"x":[0.5],"y":[1]},"o":{"x":[0.5],"y":[0]},"t":44,"s":[85]},{"i":{"x":[0.5],"y":[1]},"o":{"x":[0.5],"y":[0]},"t":54,"s":[0]},{"t":120,"s":[0]}],"ix":11},"r":{"a":0,"k":0,"ix":10},"p":{"a":0,"k":[90,74,0],"ix":2},"a":{"a":0,"k":[0,0,0],"ix":1},"s":{"a":1,"k":[{"i":{"x":[0.5,0.5,0.5],"y":[1,1,1]},"o":{"x":[0.5,0.5,0.5],"y":[0,0,0]},"t":40,"s":[0,0,100]},{"i":{"x":[0.5,0.5,0.5],"y":[1,1,1]},"o":{"x":[0.5,0.5,0.5],"y":[0,0,0]},"t":44,"s":[130,130,100]},{"t":50,"s":[100,100,100]}],"ix":6}},"ao":0,"shapes":[{"ty":"gr","it":[{"ty":"sh","d":1,"ks":{"a":0,"k":{"i":[[0,0],[0,0]],"o":[[0,0],[0,0]],"v":[[22,0],[40,0]],"c":false},"ix":2},"nm":"sh","mn":"ADBE Vector Shape - Group","hd":false},{"ty":"st","c":{"a":0,"k":[0.98,0.94,0.78,1],"ix":3},"o":{"a":0,"k":100,"ix":4},"w":{"a":0,"k":3,"ix":5},"lc":2,"lj":2,"ml":4,"bm":0,"nm":"st","mn":"ADBE Vector Graphic - Stroke","hd":false},{"ty":"tr","p":{"a":0,"k":[0,0],"ix":2},"a":{"a":0,"k":[0,0],"ix":1},"s":{"a":0,"k":[100,100],"ix":3},"r":{"a":0,"k":0,"ix":6},"o":{"a":0,"k":100,"ix":7},"sk":{"a":0,"k":0,"ix":4},"sa":{"a":0,"k":0,"ix":5},"nm":"Transform"}],"nm":"g","np":2,"cix":2,"bm":0,"ix":1,"mn":"ADBE Vector Group","hd":false}],"ip":0,"op":120,"st":0,"bm":0},{"ddd":0,"ind":2,"ty":4,"nm":"ray_0_1","sr":1,"ks":{"o":{"a":1,"k":[{"i":{"x":[0.5],"y":[1]},"o":{"x":[0.5],"y":[0]},"t":40,"s":[0]},{"i":{"x":[0.5],"y":[1]},"o":{"x":[0.5],"y":[0]},"t":44,"s":[85]},{"i":{"x":[0.5],"y":[1]},"o":{"x":[0.5],"y":[0]},"t":54,"s":[0]},{"t":120,"s":[0]}],"ix":11},"r":{"a":0,"k":0,"ix":10},"p":{"a":0,"k":[90,74,0],"ix":2},"a":{"a":0,"k":[0,0,0],"ix":1},"s":{"a":1,"k":[{"i":{"x":[0.5,0.5,0.5],"y":[1,1,1]},"o":{"x":[0.5,0.5,0.5],"y":[0,0,0]},"t":40,"s":[0,0,100]},{"i":{"x":[0.5,0.5,0.5],"y":[1,1,1]},"o":{"x":[0.5,0.5,0.5],"y":[0,0,0]},"t":44,"s":[130,130,100]},{"t":50,"s":[100,100,100]}],"ix":6}},"ao":0,"shapes":[{"ty":"gr","it":[{"ty":"sh","d":1,"ks":{"a":0,"k":{"i":[[0,0],[0,0]],"o":[[0,0],[0,0]],"v":[[15.556349186104047,15.556349186104043],[28.284271247461902,28.2842712474619]],"c":false},"ix":2},"nm":"sh","mn":"ADBE Vector Shape - Group","hd":false},{"ty":"st","c":{"a":0,"k":[0.98,0.94,0.78,1],"ix":3},"o":{"a":0,"k":100,"ix":4},"w":{"a":0,"k":3,"ix":5},"lc":2,"lj":2,"ml":4,"bm":0,"nm":"st","mn":"ADBE Vector Graphic - Stroke","hd":false},{"ty":"tr","p":{"a":0,"k":[0,0],"ix":2},"a":{"a":0,"k":[0,0],"ix":1},"s":{"a":0,"k":[100,100],"ix":3},"r":{"a":0,"k":0,"ix":6},"o":{"a":0,"k":100,"ix":7},"sk":{"a":0,"k":0,"ix":4},"sa":{"a":0,"k":0,"ix":5},"nm":"Transform"}],"nm":"g","np":2,"cix":2,"bm":0,"ix":1,"mn":"ADBE Vector Group","hd":false}],"ip":0,"op":120,"st":0,"bm":0},{"ddd":0,"ind":3,"ty":4,"nm":"ray_0_2","sr":1,"ks":{"o":{"a":1,"k":[{"i":{"x":[0.5],"y":[1]},"o":{"x":[0.5],"y":[0]},"t":40,"s":[0]},{"i":{"x":[0.5],"y":[1]},"o":{"x":[0.5],"y":[0]},"t":44,"s":[85]},{"i":{"x":[0.5],"y":[1]},"o":{"x":[0.5],"y":[0]},"t":54,"s":[0]},{"t":120,"s":[0]}],"ix":11},"r":{"a":0,"k":0,"ix":10},"p":{"a":0,"k":[90,74,0],"ix":2},"a":{"a":0,"k":[0,0,0],"ix":1},"s":{"a":1,"k":[{"i":{"x":[0.5,0.5,0.5],"y":[1,1,1]},"o":{"x":[0.5,0.5,0.5],"y":[0,0,0]},"t":40,"s":[0,0,100]},{"i":{"x":[0.5,0.5,0.5],"y":[1,1,1]},"o":{"x":[0.5,0.5,0.5],"y":[0,0,0]},"t":44,"s":[130,130,100]},{"t":50,"s":[100,100,100]}],"ix":6}},"ao":0,"shapes":[{"ty":"gr","it":[{"ty":"sh","d":1,"ks":{"a":0,"k":{"i":[[0,0],[0,0]],"o":[[0,0],[0,0]],"v":[[1.3471114790620886e-15,22],[2.4492935982947065e-15,40]],"c":false},"ix":2},"nm":"sh","mn":"ADBE Vector Shape - Group","hd":false},{"ty":"st","c":{"a":0,"k":[0.98,0.94,0.78,1],"ix":3},"o":{"a":0,"k":100,"ix":4},"w":{"a":0,"k":3,"ix":5},"lc":2,"lj":2,"ml":4,"bm":0,"nm":"st","mn":"ADBE Vector Graphic - Stroke","hd":false},{"ty":"tr","p":{"a":0,"k":[0,0],"ix":2},"a":{"a":0,"k":[0,0],"ix":1},"s":{"a":0,"k":[100,100],"ix":3},"r":{"a":0,"k":0,"ix":6},"o":{"a":0,"k":100,"ix":7},"sk":{"a":0,"k":0,"ix":4},"sa":{"a":0,"k":0,"ix":5},"nm":"Transform"}],"nm":"g","np":2,"cix":2,"bm":0,"ix":1,"mn":"ADBE Vector Group","hd":false}],"ip":0,"op":120,"st":0,"bm":0},{"ddd":0,"ind":4,"ty":4,"nm":"ray_0_3","sr":1,"ks":{"o":{"a":1,"k":[{"i":{"x":[0.5],"y":[1]},"o":{"x":[0.5],"y":[0]},"t":40,"s":[0]},{"i":{"x":[0.5],"y":[1]},"o":{"x":[0.5],"y":[0]},"t":44,"s":[85]},{"i":{"x":[0.5],"y":[1]},"o":{"x":[0.5],"y":[0]},"t":54,"s":[0]},{"t":120,"s":[0]}],"ix":11},"r":{"a":0,"k":0,"ix":10},"p":{"a":0,"k":[90,74,0],"ix":2},"a":{"a":0,"k":[0,0,0],"ix":1},"s":{"a":1,"k":[{"i":{"x":[0.5,0.5,0.5],"y":[1,1,1]},"o":{"x":[0.5,0.5,0.5],"y":[0,0,0]},"t":40,"s":[0,0,100]},{"i":{"x":[0.5,0.5,0.5],"y":[1,1,1]},"o":{"x":[0.5,0.5,0.5],"y":[0,0,0]},"t":44,"s":[130,130,100]},{"t":50,"s":[100,100,100]}],"ix":6}},"ao":0,"shapes":[{"ty":"gr","it":[{"ty":"sh","d":1,"ks":{"a":0,"k":{"i":[[0,0],[0,0]],"o":[[0,0],[0,0]],"v":[[-15.556349186104043,15.556349186104047],[-28.2842712474619,28.284271247461902]],"c":false},"ix":2},"nm":"sh","mn":"ADBE Vector Shape - Group","hd":false},{"ty":"st","c":{"a":0,"k":[0.98,0.94,0.78,1],"ix":3},"o":{"a":0,"k":100,"ix":4},"w":{"a":0,"k":3,"ix":5},"lc":2,"lj":2,"ml":4,"bm":0,"nm":"st","mn":"ADBE Vector Graphic - Stroke","hd":false},{"ty":"tr","p":{"a":0,"k":[0,0],"ix":2},"a":{"a":0,"k":[0,0],"ix":1},"s":{"a":0,"k":[100,100],"ix":3},"r":{"a":0,"k":0,"ix":6},"o":{"a":0,"k":100,"ix":7},"sk":{"a":0,"k":0,"ix":4},"sa":{"a":0,"k":0,"ix":5},"nm":"Transform"}],"nm":"g","np":2,"cix":2,"bm":0,"ix":1,"mn":"ADBE Vector Group","hd":false}],"ip":0,"op":120,"st":0,"bm":0},{"ddd":0,"ind":5,"ty":4,"nm":"ray_0_4","sr":1,"ks":{"o":{"a":1,"k":[{"i":{"x":[0.5],"y":[1]},"o":{"x":[0.5],"y":[0]},"t":40,"s":[0]},{"i":{"x":[0.5],"y":[1]},"o":{"x":[0.5],"y":[0]},"t":44,"s":[85]},{"i":{"x":[0.5],"y":[1]},"o":{"x":[0.5],"y":[0]},"t":54,"s":[0]},{"t":120,"s":[0]}],"ix":11},"r":{"a":0,"k":0,"ix":10},"p":{"a":0,"k":[90,74,0],"ix":2},"a":{"a":0,"k":[0,0,0],"ix":1},"s":{"a":1,"k":[{"i":{"x":[0.5,0.5,0.5],"y":[1,1,1]},"o":{"x":[0.5,0.5,0.5],"y":[0,0,0]},"t":40,"s":[0,0,100]},{"i":{"x":[0.5,0.5,0.5],"y":[1,1,1]},"o":{"x":[0.5,0.5,0.5],"y":[0,0,0]},"t":44,"s":[130,130,100]},{"t":50,"s":[100,100,100]}],"ix":6}},"ao":0,"shapes":[{"ty":"gr","it":[{"ty":"sh","d":1,"ks":{"a":0,"k":{"i":[[0,0],[0,0]],"o":[[0,0],[0,0]],"v":[[-22,2.6942229581241772e-15],[-40,4.898587196589413e-15]],"c":false},"ix":2},"nm":"sh","mn":"ADBE Vector Shape - Group","hd":false},{"ty":"st","c":{"a":0,"k":[0.98,0.94,0.78,1],"ix":3},"o":{"a":0,"k":100,"ix":4},"w":{"a":0,"k":3,"ix":5},"lc":2,"lj":2,"ml":4,"bm":0,"nm":"st","mn":"ADBE Vector Graphic - Stroke","hd":false},{"ty":"tr","p":{"a":0,"k":[0,0],"ix":2},"a":{"a":0,"k":[0,0],"ix":1},"s":{"a":0,"k":[100,100],"ix":3},"r":{"a":0,"k":0,"ix":6},"o":{"a":0,"k":100,"ix":7},"sk":{"a":0,"k":0,"ix":4},"sa":{"a":0,"k":0,"ix":5},"nm":"Transform"}],"nm":"g","np":2,"cix":2,"bm":0,"ix":1,"mn":"ADBE Vector Group","hd":false}],"ip":0,"op":120,"st":0,"bm":0},{"ddd":0,"ind":6,"ty":4,"nm":"ray_0_5","sr":1,"ks":{"o":{"a":1,"k":[{"i":{"x":[0.5],"y":[1]},"o":{"x":[0.5],"y":[0]},"t":40,"s":[0]},{"i":{"x":[0.5],"y":[1]},"o":{"x":[0.5],"y":[0]},"t":44,"s":[85]},{"i":{"x":[0.5],"y":[1]},"o":{"x":[0.5],"y":[0]},"t":54,"s":[0]},{"t":120,"s":[0]}],"ix":11},"r":{"a":0,"k":0,"ix":10},"p":{"a":0,"k":[90,74,0],"ix":2},"a":{"a":0,"k":[0,0,0],"ix":1},"s":{"a":1,"k":[{"i":{"x":[0.5,0.5,0.5],"y":[1,1,1]},"o":{"x":[0.5,0.5,0.5],"y":[0,0,0]},"t":40,"s":[0,0,100]},{"i":{"x":[0.5,0.5,0.5],"y":[1,1,1]},"o":{"x":[0.5,0.5,0.5],"y":[0,0,0]},"t":44,"s":[130,130,100]},{"t":50,"s":[100,100,100]}],"ix":6}},"ao":0,"shapes":[{"ty":"gr","it":[{"ty":"sh","d":1,"ks":{"a":0,"k":{"i":[[0,0],[0,0]],"o":[[0,0],[0,0]],"v":[[-15.556349186104049,-15.556349186104043],[-28.28427124746191,-28.2842712474619]],"c":false},"ix":2},"nm":"sh","mn":"ADBE Vector Shape - Group","hd":false},{"ty":"st","c":{"a":0,"k":[0.98,0.94,0.78,1],"ix":3},"o":{"a":0,"k":100,"ix":4},"w":{"a":0,"k":3,"ix":5},"lc":2,"lj":2,"ml":4,"bm":0,"nm":"st","mn":"ADBE Vector Graphic - Stroke","hd":false},{"ty":"tr","p":{"a":0,"k":[0,0],"ix":2},"a":{"a":0,"k":[0,0],"ix":1},"s":{"a":0,"k":[100,100],"ix":3},"r":{"a":0,"k":0,"ix":6},"o":{"a":0,"k":100,"ix":7},"sk":{"a":0,"k":0,"ix":4},"sa":{"a":0,"k":0,"ix":5},"nm":"Transform"}],"nm":"g","np":2,"cix":2,"bm":0,"ix":1,"mn":"ADBE Vector Group","hd":false}],"ip":0,"op":120,"st":0,"bm":0},{"ddd":0,"ind":7,"ty":4,"nm":"ray_0_6","sr":1,"ks":{"o":{"a":1,"k":[{"i":{"x":[0.5],"y":[1]},"o":{"x":[0.5],"y":[0]},"t":40,"s":[0]},{"i":{"x":[0.5],"y":[1]},"o":{"x":[0.5],"y":[0]},"t":44,"s":[85]},{"i":{"x":[0.5],"y":[1]},"o":{"x":[0.5],"y":[0]},"t":54,"s":[0]},{"t":120,"s":[0]}],"ix":11},"r":{"a":0,"k":0,"ix":10},"p":{"a":0,"k":[90,74,0],"ix":2},"a":{"a":0,"k":[0,0,0],"ix":1},"s":{"a":1,"k":[{"i":{"x":[0.5,0.5,0.5],"y":[1,1,1]},"o":{"x":[0.5,0.5,0.5],"y":[0,0,0]},"t":40,"s":[0,0,100]},{"i":{"x":[0.5,0.5,0.5],"y":[1,1,1]},"o":{"x":[0.5,0.5,0.5],"y":[0,0,0]},"t":44,"s":[130,130,100]},{"t":50,"s":[100,100,100]}],"ix":6}},"ao":0,"shapes":[{"ty":"gr","it":[{"ty":"sh","d":1,"ks":{"a":0,"k":{"i":[[0,0],[0,0]],"o":[[0,0],[0,0]],"v":[[-4.0413344371862654e-15,-22],[-7.347880794884118e-15,-40]],"c":false},"ix":2},"nm":"sh","mn":"ADBE Vector Shape - Group","hd":false},{"ty":"st","c":{"a":0,"k":[0.98,0.94,0.78,1],"ix":3},"o":{"a":0,"k":100,"ix":4},"w":{"a":0,"k":3,"ix":5},"lc":2,"lj":2,"ml":4,"bm":0,"nm":"st","mn":"ADBE Vector Graphic - Stroke","hd":false},{"ty":"tr","p":{"a":0,"k":[0,0],"ix":2},"a":{"a":0,"k":[0,0],"ix":1},"s":{"a":0,"k":[100,100],"ix":3},"r":{"a":0,"k":0,"ix":6},"o":{"a":0,"k":100,"ix":7},"sk":{"a":0,"k":0,"ix":4},"sa":{"a":0,"k":0,"ix":5},"nm":"Transform"}],"nm":"g","np":2,"cix":2,"bm":0,"ix":1,"mn":"ADBE Vector Group","hd":false}],"ip":0,"op":120,"st":0,"bm":0},{"ddd":0,"ind":8,"ty":4,"nm":"ray_0_7","sr":1,"ks":{"o":{"a":1,"k":[{"i":{"x":[0.5],"y":[1]},"o":{"x":[0.5],"y":[0]},"t":40,"s":[0]},{"i":{"x":[0.5],"y":[1]},"o":{"x":[0.5],"y":[0]},"t":44,"s":[85]},{"i":{"x":[0.5],"y":[1]},"o":{"x":[0.5],"y":[0]},"t":54,"s":[0]},{"t":120,"s":[0]}],"ix":11},"r":{"a":0,"k":0,"ix":10},"p":{"a":0,"k":[90,74,0],"ix":2},"a":{"a":0,"k":[0,0,0],"ix":1},"s":{"a":1,"k":[{"i":{"x":[0.5,0.5,0.5],"y":[1,1,1]},"o":{"x":[0.5,0.5,0.5],"y":[0,0,0]},"t":40,"s":[0,0,100]},{"i":{"x":[0.5,0.5,0.5],"y":[1,1,1]},"o":{"x":[0.5,0.5,0.5],"y":[0,0,0]},"t":44,"s":[130,130,100]},{"t":50,"s":[100,100,100]}],"ix":6}},"ao":0,"shapes":[{"ty":"gr","it":[{"ty":"sh","d":1,"ks":{"a":0,"k":{"i":[[0,0],[0,0]],"o":[[0,0],[0,0]],"v":[[15.556349186104041,-15.556349186104049],[28.284271247461895,-28.28427124746191]],"c":false},"ix":2},"nm":"sh","mn":"ADBE Vector Shape - Group","hd":false},{"ty":"st","c":{"a":0,"k":[0.98,0.94,0.78,1],"ix":3},"o":{"a":0,"k":100,"ix":4},"w":{"a":0,"k":3,"ix":5},"lc":2,"lj":2,"ml":4,"bm":0,"nm":"st","mn":"ADBE Vector Graphic - Stroke","hd":false},{"ty":"tr","p":{"a":0,"k":[0,0],"ix":2},"a":{"a":0,"k":[0,0],"ix":1},"s":{"a":0,"k":[100,100],"ix":3},"r":{"a":0,"k":0,"ix":6},"o":{"a":0,"k":100,"ix":7},"sk":{"a":0,"k":0,"ix":4},"sa":{"a":0,"k":0,"ix":5},"nm":"Transform"}],"nm":"g","np":2,"cix":2,"bm":0,"ix":1,"mn":"ADBE Vector Group","hd":false}],"ip":0,"op":120,"st":0,"bm":0},{"ddd":0,"ind":9,"ty":4,"nm":"ray_1_0","sr":1,"ks":{"o":{"a":1,"k":[{"i":{"x":[0.5],"y":[1]},"o":{"x":[0.5],"y":[0]},"t":86,"s":[0]},{"i":{"x":[0.5],"y":[1]},"o":{"x":[0.5],"y":[0]},"t":90,"s":[85]},{"i":{"x":[0.5],"y":[1]},"o":{"x":[0.5],"y":[0]},"t":100,"s":[0]},{"t":120,"s":[0]}],"ix":11},"r":{"a":0,"k":0,"ix":10},"p":{"a":0,"k":[90,74,0],"ix":2},"a":{"a":0,"k":[0,0,0],"ix":1},"s":{"a":1,"k":[{"i":{"x":[0.5,0.5,0.5],"y":[1,1,1]},"o":{"x":[0.5,0.5,0.5],"y":[0,0,0]},"t":86,"s":[0,0,100]},{"i":{"x":[0.5,0.5,0.5],"y":[1,1,1]},"o":{"x":[0.5,0.5,0.5],"y":[0,0,0]},"t":90,"s":[130,130,100]},{"t":96,"s":[100,100,100]}],"ix":6}},"ao":0,"shapes":[{"ty":"gr","it":[{"ty":"sh","d":1,"ks":{"a":0,"k":{"i":[[0,0],[0,0]],"o":[[0,0],[0,0]],"v":[[22,0],[40,0]],"c":false},"ix":2},"nm":"sh","mn":"ADBE Vector Shape - Group","hd":false},{"ty":"st","c":{"a":0,"k":[0.98,0.94,0.78,1],"ix":3},"o":{"a":0,"k":100,"ix":4},"w":{"a":0,"k":3,"ix":5},"lc":2,"lj":2,"ml":4,"bm":0,"nm":"st","mn":"ADBE Vector Graphic - Stroke","hd":false},{"ty":"tr","p":{"a":0,"k":[0,0],"ix":2},"a":{"a":0,"k":[0,0],"ix":1},"s":{"a":0,"k":[100,100],"ix":3},"r":{"a":0,"k":0,"ix":6},"o":{"a":0,"k":100,"ix":7},"sk":{"a":0,"k":0,"ix":4},"sa":{"a":0,"k":0,"ix":5},"nm":"Transform"}],"nm":"g","np":2,"cix":2,"bm":0,"ix":1,"mn":"ADBE Vector Group","hd":false}],"ip":0,"op":120,"st":0,"bm":0},{"ddd":0,"ind":10,"ty":4,"nm":"ray_1_1","sr":1,"ks":{"o":{"a":1,"k":[{"i":{"x":[0.5],"y":[1]},"o":{"x":[0.5],"y":[0]},"t":86,"s":[0]},{"i":{"x":[0.5],"y":[1]},"o":{"x":[0.5],"y":[0]},"t":90,"s":[85]},{"i":{"x":[0.5],"y":[1]},"o":{"x":[0.5],"y":[0]},"t":100,"s":[0]},{"t":120,"s":[0]}],"ix":11},"r":{"a":0,"k":0,"ix":10},"p":{"a":0,"k":[90,74,0],"ix":2},"a":{"a":0,"k":[0,0,0],"ix":1},"s":{"a":1,"k":[{"i":{"x":[0.5,0.5,0.5],"y":[1,1,1]},"o":{"x":[0.5,0.5,0.5],"y":[0,0,0]},"t":86,"s":[0,0,100]},{"i":{"x":[0.5,0.5,0.5],"y":[1,1,1]},"o":{"x":[0.5,0.5,0.5],"y":[0,0,0]},"t":90,"s":[130,130,100]},{"t":96,"s":[100,100,100]}],"ix":6}},"ao":0,"shapes":[{"ty":"gr","it":[{"ty":"sh","d":1,"ks":{"a":0,"k":{"i":[[0,0],[0,0]],"o":[[0,0],[0,0]],"v":[[15.556349186104047,15.556349186104043],[28.284271247461902,28.2842712474619]],"c":false},"ix":2},"nm":"sh","mn":"ADBE Vector Shape - Group","hd":false},{"ty":"st","c":{"a":0,"k":[0.98,0.94,0.78,1],"ix":3},"o":{"a":0,"k":100,"ix":4},"w":{"a":0,"k":3,"ix":5},"lc":2,"lj":2,"ml":4,"bm":0,"nm":"st","mn":"ADBE Vector Graphic - Stroke","hd":false},{"ty":"tr","p":{"a":0,"k":[0,0],"ix":2},"a":{"a":0,"k":[0,0],"ix":1},"s":{"a":0,"k":[100,100],"ix":3},"r":{"a":0,"k":0,"ix":6},"o":{"a":0,"k":100,"ix":7},"sk":{"a":0,"k":0,"ix":4},"sa":{"a":0,"k":0,"ix":5},"nm":"Transform"}],"nm":"g","np":2,"cix":2,"bm":0,"ix":1,"mn":"ADBE Vector Group","hd":false}],"ip":0,"op":120,"st":0,"bm":0},{"ddd":0,"ind":11,"ty":4,"nm":"ray_1_2","sr":1,"ks":{"o":{"a":1,"k":[{"i":{"x":[0.5],"y":[1]},"o":{"x":[0.5],"y":[0]},"t":86,"s":[0]},{"i":{"x":[0.5],"y":[1]},"o":{"x":[0.5],"y":[0]},"t":90,"s":[85]},{"i":{"x":[0.5],"y":[1]},"o":{"x":[0.5],"y":[0]},"t":100,"s":[0]},{"t":120,"s":[0]}],"ix":11},"r":{"a":0,"k":0,"ix":10},"p":{"a":0,"k":[90,74,0],"ix":2},"a":{"a":0,"k":[0,0,0],"ix":1},"s":{"a":1,"k":[{"i":{"x":[0.5,0.5,0.5],"y":[1,1,1]},"o":{"x":[0.5,0.5,0.5],"y":[0,0,0]},"t":86,"s":[0,0,100]},{"i":{"x":[0.5,0.5,0.5],"y":[1,1,1]},"o":{"x":[0.5,0.5,0.5],"y":[0,0,0]},"t":90,"s":[130,130,100]},{"t":96,"s":[100,100,100]}],"ix":6}},"ao":0,"shapes":[{"ty":"gr","it":[{"ty":"sh","d":1,"ks":{"a":0,"k":{"i":[[0,0],[0,0]],"o":[[0,0],[0,0]],"v":[[1.3471114790620886e-15,22],[2.4492935982947065e-15,40]],"c":false},"ix":2},"nm":"sh","mn":"ADBE Vector Shape - Group","hd":false},{"ty":"st","c":{"a":0,"k":[0.98,0.94,0.78,1],"ix":3},"o":{"a":0,"k":100,"ix":4},"w":{"a":0,"k":3,"ix":5},"lc":2,"lj":2,"ml":4,"bm":0,"nm":"st","mn":"ADBE Vector Graphic - Stroke","hd":false},{"ty":"tr","p":{"a":0,"k":[0,0],"ix":2},"a":{"a":0,"k":[0,0],"ix":1},"s":{"a":0,"k":[100,100],"ix":3},"r":{"a":0,"k":0,"ix":6},"o":{"a":0,"k":100,"ix":7},"sk":{"a":0,"k":0,"ix":4},"sa":{"a":0,"k":0,"ix":5},"nm":"Transform"}],"nm":"g","np":2,"cix":2,"bm":0,"ix":1,"mn":"ADBE Vector Group","hd":false}],"ip":0,"op":120,"st":0,"bm":0},{"ddd":0,"ind":12,"ty":4,"nm":"ray_1_3","sr":1,"ks":{"o":{"a":1,"k":[{"i":{"x":[0.5],"y":[1]},"o":{"x":[0.5],"y":[0]},"t":86,"s":[0]},{"i":{"x":[0.5],"y":[1]},"o":{"x":[0.5],"y":[0]},"t":90,"s":[85]},{"i":{"x":[0.5],"y":[1]},"o":{"x":[0.5],"y":[0]},"t":100,"s":[0]},{"t":120,"s":[0]}],"ix":11},"r":{"a":0,"k":0,"ix":10},"p":{"a":0,"k":[90,74,0],"ix":2},"a":{"a":0,"k":[0,0,0],"ix":1},"s":{"a":1,"k":[{"i":{"x":[0.5,0.5,0.5],"y":[1,1,1]},"o":{"x":[0.5,0.5,0.5],"y":[0,0,0]},"t":86,"s":[0,0,100]},{"i":{"x":[0.5,0.5,0.5],"y":[1,1,1]},"o":{"x":[0.5,0.5,0.5],"y":[0,0,0]},"t":90,"s":[130,130,100]},{"t":96,"s":[100,100,100]}],"ix":6}},"ao":0,"shapes":[{"ty":"gr","it":[{"ty":"sh","d":1,"ks":{"a":0,"k":{"i":[[0,0],[0,0]],"o":[[0,0],[0,0]],"v":[[-15.556349186104043,15.556349186104047],[-28.2842712474619,28.284271247461902]],"c":false},"ix":2},"nm":"sh","mn":"ADBE Vector Shape - Group","hd":false},{"ty":"st","c":{"a":0,"k":[0.98,0.94,0.78,1],"ix":3},"o":{"a":0,"k":100,"ix":4},"w":{"a":0,"k":3,"ix":5},"lc":2,"lj":2,"ml":4,"bm":0,"nm":"st","mn":"ADBE Vector Graphic - Stroke","hd":false},{"ty":"tr","p":{"a":0,"k":[0,0],"ix":2},"a":{"a":0,"k":[0,0],"ix":1},"s":{"a":0,"k":[100,100],"ix":3},"r":{"a":0,"k":0,"ix":6},"o":{"a":0,"k":100,"ix":7},"sk":{"a":0,"k":0,"ix":4},"sa":{"a":0,"k":0,"ix":5},"nm":"Transform"}],"nm":"g","np":2,"cix":2,"bm":0,"ix":1,"mn":"ADBE Vector Group","hd":false}],"ip":0,"op":120,"st":0,"bm":0},{"ddd":0,"ind":13,"ty":4,"nm":"ray_1_4","sr":1,"ks":{"o":{"a":1,"k":[{"i":{"x":[0.5],"y":[1]},"o":{"x":[0.5],"y":[0]},"t":86,"s":[0]},{"i":{"x":[0.5],"y":[1]},"o":{"x":[0.5],"y":[0]},"t":90,"s":[85]},{"i":{"x":[0.5],"y":[1]},"o":{"x":[0.5],"y":[0]},"t":100,"s":[0]},{"t":120,"s":[0]}],"ix":11},"r":{"a":0,"k":0,"ix":10},"p":{"a":0,"k":[90,74,0],"ix":2},"a":{"a":0,"k":[0,0,0],"ix":1},"s":{"a":1,"k":[{"i":{"x":[0.5,0.5,0.5],"y":[1,1,1]},"o":{"x":[0.5,0.5,0.5],"y":[0,0,0]},"t":86,"s":[0,0,100]},{"i":{"x":[0.5,0.5,0.5],"y":[1,1,1]},"o":{"x":[0.5,0.5,0.5],"y":[0,0,0]},"t":90,"s":[130,130,100]},{"t":96,"s":[100,100,100]}],"ix":6}},"ao":0,"shapes":[{"ty":"gr","it":[{"ty":"sh","d":1,"ks":{"a":0,"k":{"i":[[0,0],[0,0]],"o":[[0,0],[0,0]],"v":[[-22,2.6942229581241772e-15],[-40,4.898587196589413e-15]],"c":false},"ix":2},"nm":"sh","mn":"ADBE Vector Shape - Group","hd":false},{"ty":"st","c":{"a":0,"k":[0.98,0.94,0.78,1],"ix":3},"o":{"a":0,"k":100,"ix":4},"w":{"a":0,"k":3,"ix":5},"lc":2,"lj":2,"ml":4,"bm":0,"nm":"st","mn":"ADBE Vector Graphic - Stroke","hd":false},{"ty":"tr","p":{"a":0,"k":[0,0],"ix":2},"a":{"a":0,"k":[0,0],"ix":1},"s":{"a":0,"k":[100,100],"ix":3},"r":{"a":0,"k":0,"ix":6},"o":{"a":0,"k":100,"ix":7},"sk":{"a":0,"k":0,"ix":4},"sa":{"a":0,"k":0,"ix":5},"nm":"Transform"}],"nm":"g","np":2,"cix":2,"bm":0,"ix":1,"mn":"ADBE Vector Group","hd":false}],"ip":0,"op":120,"st":0,"bm":0},{"ddd":0,"ind":14,"ty":4,"nm":"ray_1_5","sr":1,"ks":{"o":{"a":1,"k":[{"i":{"x":[0.5],"y":[1]},"o":{"x":[0.5],"y":[0]},"t":86,"s":[0]},{"i":{"x":[0.5],"y":[1]},"o":{"x":[0.5],"y":[0]},"t":90,"s":[85]},{"i":{"x":[0.5],"y":[1]},"o":{"x":[0.5],"y":[0]},"t":100,"s":[0]},{"t":120,"s":[0]}],"ix":11},"r":{"a":0,"k":0,"ix":10},"p":{"a":0,"k":[90,74,0],"ix":2},"a":{"a":0,"k":[0,0,0],"ix":1},"s":{"a":1,"k":[{"i":{"x":[0.5,0.5,0.5],"y":[1,1,1]},"o":{"x":[0.5,0.5,0.5],"y":[0,0,0]},"t":86,"s":[0,0,100]},{"i":{"x":[0.5,0.5,0.5],"y":[1,1,1]},"o":{"x":[0.5,0.5,0.5],"y":[0,0,0]},"t":90,"s":[130,130,100]},{"t":96,"s":[100,100,100]}],"ix":6}},"ao":0,"shapes":[{"ty":"gr","it":[{"ty":"sh","d":1,"ks":{"a":0,"k":{"i":[[0,0],[0,0]],"o":[[0,0],[0,0]],"v":[[-15.556349186104049,-15.556349186104043],[-28.28427124746191,-28.2842712474619]],"c":false},"ix":2},"nm":"sh","mn":"ADBE Vector Shape - Group","hd":false},{"ty":"st","c":{"a":0,"k":[0.98,0.94,0.78,1],"ix":3},"o":{"a":0,"k":100,"ix":4},"w":{"a":0,"k":3,"ix":5},"lc":2,"lj":2,"ml":4,"bm":0,"nm":"st","mn":"ADBE Vector Graphic - Stroke","hd":false},{"ty":"tr","p":{"a":0,"k":[0,0],"ix":2},"a":{"a":0,"k":[0,0],"ix":1},"s":{"a":0,"k":[100,100],"ix":3},"r":{"a":0,"k":0,"ix":6},"o":{"a":0,"k":100,"ix":7},"sk":{"a":0,"k":0,"ix":4},"sa":{"a":0,"k":0,"ix":5},"nm":"Transform"}],"nm":"g","np":2,"cix":2,"bm":0,"ix":1,"mn":"ADBE Vector Group","hd":false}],"ip":0,"op":120,"st":0,"bm":0},{"ddd":0,"ind":15,"ty":4,"nm":"ray_1_6","sr":1,"ks":{"o":{"a":1,"k":[{"i":{"x":[0.5],"y":[1]},"o":{"x":[0.5],"y":[0]},"t":86,"s":[0]},{"i":{"x":[0.5],"y":[1]},"o":{"x":[0.5],"y":[0]},"t":90,"s":[85]},{"i":{"x":[0.5],"y":[1]},"o":{"x":[0.5],"y":[0]},"t":100,"s":[0]},{"t":120,"s":[0]}],"ix":11},"r":{"a":0,"k":0,"ix":10},"p":{"a":0,"k":[90,74,0],"ix":2},"a":{"a":0,"k":[0,0,0],"ix":1},"s":{"a":1,"k":[{"i":{"x":[0.5,0.5,0.5],"y":[1,1,1]},"o":{"x":[0.5,0.5,0.5],"y":[0,0,0]},"t":86,"s":[0,0,100]},{"i":{"x":[0.5,0.5,0.5],"y":[1,1,1]},"o":{"x":[0.5,0.5,0.5],"y":[0,0,0]},"t":90,"s":[130,130,100]},{"t":96,"s":[100,100,100]}],"ix":6}},"ao":0,"shapes":[{"ty":"gr","it":[{"ty":"sh","d":1,"ks":{"a":0,"k":{"i":[[0,0],[0,0]],"o":[[0,0],[0,0]],"v":[[-4.0413344371862654e-15,-22],[-7.347880794884118e-15,-40]],"c":false},"ix":2},"nm":"sh","mn":"ADBE Vector Shape - Group","hd":false},{"ty":"st","c":{"a":0,"k":[0.98,0.94,0.78,1],"ix":3},"o":{"a":0,"k":100,"ix":4},"w":{"a":0,"k":3,"ix":5},"lc":2,"lj":2,"ml":4,"bm":0,"nm":"st","mn":"ADBE Vector Graphic - Stroke","hd":false},{"ty":"tr","p":{"a":0,"k":[0,0],"ix":2},"a":{"a":0,"k":[0,0],"ix":1},"s":{"a":0,"k":[100,100],"ix":3},"r":{"a":0,"k":0,"ix":6},"o":{"a":0,"k":100,"ix":7},"sk":{"a":0,"k":0,"ix":4},"sa":{"a":0,"k":0,"ix":5},"nm":"Transform"}],"nm":"g","np":2,"cix":2,"bm":0,"ix":1,"mn":"ADBE Vector Group","hd":false}],"ip":0,"op":120,"st":0,"bm":0},{"ddd":0,"ind":16,"ty":4,"nm":"ray_1_7","sr":1,"ks":{"o":{"a":1,"k":[{"i":{"x":[0.5],"y":[1]},"o":{"x":[0.5],"y":[0]},"t":86,"s":[0]},{"i":{"x":[0.5],"y":[1]},"o":{"x":[0.5],"y":[0]},"t":90,"s":[85]},{"i":{"x":[0.5],"y":[1]},"o":{"x":[0.5],"y":[0]},"t":100,"s":[0]},{"t":120,"s":[0]}],"ix":11},"r":{"a":0,"k":0,"ix":10},"p":{"a":0,"k":[90,74,0],"ix":2},"a":{"a":0,"k":[0,0,0],"ix":1},"s":{"a":1,"k":[{"i":{"x":[0.5,0.5,0.5],"y":[1,1,1]},"o":{"x":[0.5,0.5,0.5],"y":[0,0,0]},"t":86,"s":[0,0,100]},{"i":{"x":[0.5,0.5,0.5],"y":[1,1,1]},"o":{"x":[0.5,0.5,0.5],"y":[0,0,0]},"t":90,"s":[130,130,100]},{"t":96,"s":[100,100,100]}],"ix":6}},"ao":0,"shapes":[{"ty":"gr","it":[{"ty":"sh","d":1,"ks":{"a":0,"k":{"i":[[0,0],[0,0]],"o":[[0,0],[0,0]],"v":[[15.556349186104041,-15.556349186104049],[28.284271247461895,-28.28427124746191]],"c":false},"ix":2},"nm":"sh","mn":"ADBE Vector Shape - Group","hd":false},{"ty":"st","c":{"a":0,"k":[0.98,0.94,0.78,1],"ix":3},"o":{"a":0,"k":100,"ix":4},"w":{"a":0,"k":3,"ix":5},"lc":2,"lj":2,"ml":4,"bm":0,"nm":"st","mn":"ADBE Vector Graphic - Stroke","hd":false},{"ty":"tr","p":{"a":0,"k":[0,0],"ix":2},"a":{"a":0,"k":[0,0],"ix":1},"s":{"a":0,"k":[100,100],"ix":3},"r":{"a":0,"k":0,"ix":6},"o":{"a":0,"k":100,"ix":7},"sk":{"a":0,"k":0,"ix":4},"sa":{"a":0,"k":0,"ix":5},"nm":"Transform"}],"nm":"g","np":2,"cix":2,"bm":0,"ix":1,"mn":"ADBE Vector Group","hd":false}],"ip":0,"op":120,"st":0,"bm":0},{"ddd":0,"ind":17,"ty":4,"nm":"lensFlash0","sr":1,"ks":{"o":{"a":1,"k":[{"i":{"x":[0.5],"y":[1]},"o":{"x":[0.5],"y":[0]},"t":40,"s":[0]},{"i":{"x":[0.5],"y":[1]},"o":{"x":[0.5],"y":[0]},"t":43,"s":[85]},{"i":{"x":[0.5],"y":[1]},"o":{"x":[0.5],"y":[0]},"t":52,"s":[0]},{"t":120,"s":[0]}],"ix":11},"r":{"a":0,"k":0,"ix":10},"p":{"a":0,"k":[90,74,0],"ix":2},"a":{"a":0,"k":[0,0,0],"ix":1},"s":{"a":1,"k":[{"i":{"x":[0.5,0.5,0.5],"y":[1,1,1]},"o":{"x":[0.5,0.5,0.5],"y":[0,0,0]},"t":40,"s":[0,0,100]},{"i":{"x":[0.5,0.5,0.5],"y":[1,1,1]},"o":{"x":[0.5,0.5,0.5],"y":[0,0,0]},"t":43,"s":[110,110,100]},{"t":48,"s":[100,100,100]}],"ix":6}},"ao":0,"shapes":[{"ty":"gr","it":[{"ty":"el","d":1,"s":{"a":0,"k":[36,36],"ix":2},"p":{"a":0,"k":[0,0],"ix":3},"nm":"el","mn":"ADBE Vector Shape - Ellipse","hd":false},{"ty":"fl","c":{"a":0,"k":[0.98,0.94,0.78,1],"ix":4},"o":{"a":0,"k":100,"ix":5},"r":1,"bm":0,"nm":"fl","mn":"ADBE Vector Graphic - Fill","hd":false},{"ty":"tr","p":{"a":0,"k":[0,0],"ix":2},"a":{"a":0,"k":[0,0],"ix":1},"s":{"a":0,"k":[100,100],"ix":3},"r":{"a":0,"k":0,"ix":6},"o":{"a":0,"k":100,"ix":7},"sk":{"a":0,"k":0,"ix":4},"sa":{"a":0,"k":0,"ix":5},"nm":"Transform"}],"nm":"g","np":2,"cix":2,"bm":0,"ix":1,"mn":"ADBE Vector Group","hd":false}],"ip":0,"op":120,"st":0,"bm":0},{"ddd":0,"ind":18,"ty":4,"nm":"lensFlash1","sr":1,"ks":{"o":{"a":1,"k":[{"i":{"x":[0.5],"y":[1]},"o":{"x":[0.5],"y":[0]},"t":86,"s":[0]},{"i":{"x":[0.5],"y":[1]},"o":{"x":[0.5],"y":[0]},"t":89,"s":[85]},{"i":{"x":[0.5],"y":[1]},"o":{"x":[0.5],"y":[0]},"t":98,"s":[0]},{"t":120,"s":[0]}],"ix":11},"r":{"a":0,"k":0,"ix":10},"p":{"a":0,"k":[90,74,0],"ix":2},"a":{"a":0,"k":[0,0,0],"ix":1},"s":{"a":1,"k":[{"i":{"x":[0.5,0.5,0.5],"y":[1,1,1]},"o":{"x":[0.5,0.5,0.5],"y":[0,0,0]},"t":86,"s":[0,0,100]},{"i":{"x":[0.5,0.5,0.5],"y":[1,1,1]},"o":{"x":[0.5,0.5,0.5],"y":[0,0,0]},"t":89,"s":[110,110,100]},{"t":94,"s":[100,100,100]}],"ix":6}},"ao":0,"shapes":[{"ty":"gr","it":[{"ty":"el","d":1,"s":{"a":0,"k":[36,36],"ix":2},"p":{"a":0,"k":[0,0],"ix":3},"nm":"el","mn":"ADBE Vector Shape - Ellipse","hd":false},{"ty":"fl","c":{"a":0,"k":[0.98,0.94,0.78,1],"ix":4},"o":{"a":0,"k":100,"ix":5},"r":1,"bm":0,"nm":"fl","mn":"ADBE Vector Graphic - Fill","hd":false},{"ty":"tr","p":{"a":0,"k":[0,0],"ix":2},"a":{"a":0,"k":[0,0],"ix":1},"s":{"a":0,"k":[100,100],"ix":3},"r":{"a":0,"k":0,"ix":6},"o":{"a":0,"k":100,"ix":7},"sk":{"a":0,"k":0,"ix":4},"sa":{"a":0,"k":0,"ix":5},"nm":"Transform"}],"nm":"g","np":2,"cix":2,"bm":0,"ix":1,"mn":"ADBE Vector Group","hd":false}],"ip":0,"op":120,"st":0,"bm":0},{"ddd":0,"ind":19,"ty":4,"nm":"lensInner","sr":1,"ks":{"o":{"a":1,"k":[{"i":{"x":[0.5],"y":[1]},"o":{"x":[0.5],"y":[0]},"t":14,"s":[0]},{"i":{"x":[0.5],"y":[1]},"o":{"x":[0.5],"y":[0]},"t":22,"s":[100]},{"i":{"x":[0.5],"y":[1]},"o":{"x":[0.5],"y":[0]},"t":108,"s":[100]},{"t":120,"s":[0]}],"ix":11},"r":{"a":0,"k":0,"ix":10},"p":{"a":0,"k":[90,74,0],"ix":2},"a":{"a":0,"k":[0,0,0],"ix":1},"s":{"a":1,"k":[{"i":{"x":[0.5,0.5,0.5],"y":[1,1,1]},"o":{"x":[0.5,0.5,0.5],"y":[0,0,0]},"t":14,"s":[0,0,100]},{"i":{"x":[0.5,0.5,0.5],"y":[1,1,1]},"o":{"x":[0.5,0.5,0.5],"y":[0,0,0]},"t":22,"s":[100,100,100]},{"t":30,"s":[100,100,100]}],"ix":6}},"ao":0,"shapes":[{"ty":"gr","it":[{"ty":"el","d":1,"s":{"a":0,"k":[28,28],"ix":2},"p":{"a":0,"k":[0,0],"ix":3},"nm":"el","mn":"ADBE Vector Shape - Ellipse","hd":false},{"ty":"fl","c":{"a":0,"k":[0.08,0.1,0.16,1],"ix":4},"o":{"a":0,"k":100,"ix":5},"r":1,"bm":0,"nm":"fl","mn":"ADBE Vector Graphic - Fill","hd":false},{"ty":"tr","p":{"a":0,"k":[0,0],"ix":2},"a":{"a":0,"k":[0,0],"ix":1},"s":{"a":0,"k":[100,100],"ix":3},"r":{"a":0,"k":0,"ix":6},"o":{"a":0,"k":100,"ix":7},"sk":{"a":0,"k":0,"ix":4},"sa":{"a":0,"k":0,"ix":5},"nm":"Transform"}],"nm":"g","np":2,"cix":2,"bm":0,"ix":1,"mn":"ADBE Vector Group","hd":false}],"ip":0,"op":120,"st":0,"bm":0},{"ddd":0,"ind":20,"ty":4,"nm":"lensRing","sr":1,"ks":{"o":{"a":1,"k":[{"i":{"x":[0.5],"y":[1]},"o":{"x":[0.5],"y":[0]},"t":10,"s":[0]},{"i":{"x":[0.5],"y":[1]},"o":{"x":[0.5],"y":[0]},"t":18,"s":[100]},{"i":{"x":[0.5],"y":[1]},"o":{"x":[0.5],"y":[0]},"t":108,"s":[100]},{"t":120,"s":[0]}],"ix":11},"r":{"a":0,"k":0,"ix":10},"p":{"a":0,"k":[90,74,0],"ix":2},"a":{"a":0,"k":[0,0,0],"ix":1},"s":{"a":1,"k":[{"i":{"x":[0.5,0.5,0.5],"y":[1,1,1]},"o":{"x":[0.5,0.5,0.5],"y":[0,0,0]},"t":10,"s":[0,0,100]},{"i":{"x":[0.5,0.5,0.5],"y":[1,1,1]},"o":{"x":[0.5,0.5,0.5],"y":[0,0,0]},"t":18,"s":[100,100,100]},{"t":26,"s":[100,100,100]}],"ix":6}},"ao":0,"shapes":[{"ty":"gr","it":[{"ty":"el","d":1,"s":{"a":0,"k":[40,40],"ix":2},"p":{"a":0,"k":[0,0],"ix":3},"nm":"el","mn":"ADBE Vector Shape - Ellipse","hd":false},{"ty":"fl","c":{"a":0,"k":[0.24,0.26,0.32,1],"ix":4},"o":{"a":0,"k":100,"ix":5},"r":1,"bm":0,"nm":"fl","mn":"ADBE Vector Graphic - Fill","hd":false},{"ty":"st","c":{"a":0,"k":[0.6,0.62,0.66,1],"ix":3},"o":{"a":0,"k":100,"ix":4},"w":{"a":0,"k":1.5,"ix":5},"lc":2,"lj":2,"ml":4,"bm":0,"nm":"st","mn":"ADBE Vector Graphic - Stroke","hd":false},{"ty":"tr","p":{"a":0,"k":[0,0],"ix":2},"a":{"a":0,"k":[0,0],"ix":1},"s":{"a":0,"k":[100,100],"ix":3},"r":{"a":0,"k":0,"ix":6},"o":{"a":0,"k":100,"ix":7},"sk":{"a":0,"k":0,"ix":4},"sa":{"a":0,"k":0,"ix":5},"nm":"Transform"}],"nm":"g","np":3,"cix":2,"bm":0,"ix":1,"mn":"ADBE Vector Group","hd":false}],"ip":0,"op":120,"st":0,"bm":0},{"ddd":0,"ind":21,"ty":4,"nm":"viewfinder","sr":1,"ks":{"o":{"a":1,"k":[{"i":{"x":[0.5],"y":[1]},"o":{"x":[0.5],"y":[0]},"t":6,"s":[0]},{"i":{"x":[0.5],"y":[1]},"o":{"x":[0.5],"y":[0]},"t":14,"s":[100]},{"i":{"x":[0.5],"y":[1]},"o":{"x":[0.5],"y":[0]},"t":108,"s":[100]},{"t":120,"s":[0]}],"ix":11},"r":{"a":0,"k":0,"ix":10},"p":{"a":0,"k":[124,38,0],"ix":2},"a":{"a":0,"k":[0,0,0],"ix":1},"s":{"a":1,"k":[{"i":{"x":[0.5,0.5,0.5],"y":[1,1,1]},"o":{"x":[0.5,0.5,0.5],"y":[0,0,0]},"t":6,"s":[0,0,100]},{"i":{"x":[0.5,0.5,0.5],"y":[1,1,1]},"o":{"x":[0.5,0.5,0.5],"y":[0,0,0]},"t":14,"s":[100,100,100]},{"t":22,"s":[100,100,100]}],"ix":6}},"ao":0,"shapes":[{"ty":"gr","it":[{"ty":"rc","d":1,"s":{"a":0,"k":[16,10],"ix":2},"p":{"a":0,"k":[0,0],"ix":3},"r":{"a":0,"k":1.5,"ix":4},"nm":"rc","mn":"ADBE Vector Shape - Rect","hd":false},{"ty":"fl","c":{"a":0,"k":[0.12,0.14,0.2,1],"ix":4},"o":{"a":0,"k":100,"ix":5},"r":1,"bm":0,"nm":"fl","mn":"ADBE Vector Graphic - Fill","hd":false},{"ty":"st","c":{"a":0,"k":[0.22,0.35,0.68,1],"ix":3},"o":{"a":0,"k":100,"ix":4},"w":{"a":0,"k":0.8,"ix":5},"lc":2,"lj":2,"ml":4,"bm":0,"nm":"st","mn":"ADBE Vector Graphic - Stroke","hd":false},{"ty":"tr","p":{"a":0,"k":[0,0],"ix":2},"a":{"a":0,"k":[0,0],"ix":1},"s":{"a":0,"k":[100,100],"ix":3},"r":{"a":0,"k":0,"ix":6},"o":{"a":0,"k":100,"ix":7},"sk":{"a":0,"k":0,"ix":4},"sa":{"a":0,"k":0,"ix":5},"nm":"Transform"}],"nm":"g","np":3,"cix":2,"bm":0,"ix":1,"mn":"ADBE Vector Group","hd":false}],"ip":0,"op":120,"st":0,"bm":0},{"ddd":0,"ind":22,"ty":4,"nm":"flashBulb","sr":1,"ks":{"o":{"a":1,"k":[{"i":{"x":[0.5],"y":[1]},"o":{"x":[0.5],"y":[0]},"t":0,"s":[100]},{"i":{"x":[0.5],"y":[1]},"o":{"x":[0.5],"y":[0]},"t":36,"s":[100]},{"i":{"x":[0.5],"y":[1]},"o":{"x":[0.5],"y":[0]},"t":40,"s":[60]},{"i":{"x":[0.5],"y":[1]},"o":{"x":[0.5],"y":[0]},"t":46,"s":[100]},{"i":{"x":[0.5],"y":[1]},"o":{"x":[0.5],"y":[0]},"t":82,"s":[100]},{"i":{"x":[0.5],"y":[1]},"o":{"x":[0.5],"y":[0]},"t":86,"s":[60]},{"i":{"x":[0.5],"y":[1]},"o":{"x":[0.5],"y":[0]},"t":92,"s":[100]},{"t":108,"s":[100]},{"t":120,"s":[0]}],"ix":11},"r":{"a":0,"k":0,"ix":10},"p":{"a":0,"k":[56,38,0],"ix":2},"a":{"a":0,"k":[0,0,0],"ix":1},"s":{"a":1,"k":[{"i":{"x":[0.5,0.5,0.5],"y":[1,1,1]},"o":{"x":[0.5,0.5,0.5],"y":[0,0,0]},"t":6,"s":[0,0,100]},{"i":{"x":[0.5,0.5,0.5],"y":[1,1,1]},"o":{"x":[0.5,0.5,0.5],"y":[0,0,0]},"t":14,"s":[100,100,100]},{"t":22,"s":[100,100,100]}],"ix":6}},"ao":0,"shapes":[{"ty":"gr","it":[{"ty":"rc","d":1,"s":{"a":0,"k":[14,10],"ix":2},"p":{"a":0,"k":[0,0],"ix":3},"r":{"a":0,"k":2,"ix":4},"nm":"rc","mn":"ADBE Vector Shape - Rect","hd":false},{"ty":"fl","c":{"a":0,"k":[0.98,0.94,0.78,1],"ix":4},"o":{"a":0,"k":100,"ix":5},"r":1,"bm":0,"nm":"fl","mn":"ADBE Vector Graphic - Fill","hd":false},{"ty":"st","c":{"a":0,"k":[0.22,0.35,0.68,1],"ix":3},"o":{"a":0,"k":100,"ix":4},"w":{"a":0,"k":1,"ix":5},"lc":2,"lj":2,"ml":4,"bm":0,"nm":"st","mn":"ADBE Vector Graphic - Stroke","hd":false},{"ty":"tr","p":{"a":0,"k":[0,0],"ix":2},"a":{"a":0,"k":[0,0],"ix":1},"s":{"a":0,"k":[100,100],"ix":3},"r":{"a":0,"k":0,"ix":6},"o":{"a":0,"k":100,"ix":7},"sk":{"a":0,"k":0,"ix":4},"sa":{"a":0,"k":0,"ix":5},"nm":"Transform"}],"nm":"g","np":3,"cix":2,"bm":0,"ix":1,"mn":"ADBE Vector Group","hd":false}],"ip":0,"op":120,"st":0,"bm":0},{"ddd":0,"ind":23,"ty":4,"nm":"body","sr":1,"ks":{"o":{"a":1,"k":[{"i":{"x":[0.5],"y":[1]},"o":{"x":[0.5],"y":[0]},"t":0,"s":[0]},{"i":{"x":[0.5],"y":[1]},"o":{"x":[0.5],"y":[0]},"t":8,"s":[100]},{"i":{"x":[0.5],"y":[1]},"o":{"x":[0.5],"y":[0]},"t":108,"s":[100]},{"t":120,"s":[0]}],"ix":11},"r":{"a":0,"k":0,"ix":10},"p":{"a":0,"k":[90,74,0],"ix":2},"a":{"a":0,"k":[0,0,0],"ix":1},"s":{"a":1,"k":[{"i":{"x":[0.5,0.5,0.5],"y":[1,1,1]},"o":{"x":[0.5,0.5,0.5],"y":[0,0,0]},"t":0,"s":[0,0,100]},{"i":{"x":[0.5,0.5,0.5],"y":[1,1,1]},"o":{"x":[0.5,0.5,0.5],"y":[0,0,0]},"t":8,"s":[100,100,100]},{"t":14,"s":[100,100,100]}],"ix":6}},"ao":0,"shapes":[{"ty":"gr","it":[{"ty":"rc","d":1,"s":{"a":0,"k":[128,84],"ix":2},"p":{"a":0,"k":[0,0],"ix":3},"r":{"a":0,"k":8,"ix":4},"nm":"rc","mn":"ADBE Vector Shape - Rect","hd":false},{"ty":"fl","c":{"a":0,"k":[0.22,0.35,0.68,1],"ix":4},"o":{"a":0,"k":100,"ix":5},"r":1,"bm":0,"nm":"fl","mn":"ADBE Vector Graphic - Fill","hd":false},{"ty":"st","c":{"a":0,"k":[0.1,0.14,0.24,1],"ix":3},"o":{"a":0,"k":100,"ix":4},"w":{"a":0,"k":1.2,"ix":5},"lc":2,"lj":2,"ml":4,"bm":0,"nm":"st","mn":"ADBE Vector Graphic - Stroke","hd":false},{"ty":"tr","p":{"a":0,"k":[0,0],"ix":2},"a":{"a":0,"k":[0,0],"ix":1},"s":{"a":0,"k":[100,100],"ix":3},"r":{"a":0,"k":0,"ix":6},"o":{"a":0,"k":100,"ix":7},"sk":{"a":0,"k":0,"ix":4},"sa":{"a":0,"k":0,"ix":5},"nm":"Transform"}],"nm":"g","np":3,"cix":2,"bm":0,"ix":1,"mn":"ADBE Vector Group","hd":false}],"ip":0,"op":120,"st":0,"bm":0},{"ddd":0,"ind":24,"ty":4,"nm":"bump","sr":1,"ks":{"o":{"a":1,"k":[{"i":{"x":[0.5],"y":[1]},"o":{"x":[0.5],"y":[0]},"t":0,"s":[0]},{"i":{"x":[0.5],"y":[1]},"o":{"x":[0.5],"y":[0]},"t":8,"s":[100]},{"i":{"x":[0.5],"y":[1]},"o":{"x":[0.5],"y":[0]},"t":108,"s":[100]},{"t":120,"s":[0]}],"ix":11},"r":{"a":0,"k":0,"ix":10},"p":{"a":0,"k":[90,26,0],"ix":2},"a":{"a":0,"k":[0,0,0],"ix":1},"s":{"a":0,"k":[100,100,100],"ix":6}},"ao":0,"shapes":[{"ty":"gr","it":[{"ty":"rc","d":1,"s":{"a":0,"k":[60,12],"ix":2},"p":{"a":0,"k":[0,0],"ix":3},"r":{"a":0,"k":3,"ix":4},"nm":"rc","mn":"ADBE Vector Shape - Rect","hd":false},{"ty":"fl","c":{"a":0,"k":[0.22,0.35,0.68,1],"ix":4},"o":{"a":0,"k":100,"ix":5},"r":1,"bm":0,"nm":"fl","mn":"ADBE Vector Graphic - Fill","hd":false},{"ty":"tr","p":{"a":0,"k":[0,0],"ix":2},"a":{"a":0,"k":[0,0],"ix":1},"s":{"a":0,"k":[100,100],"ix":3},"r":{"a":0,"k":0,"ix":6},"o":{"a":0,"k":100,"ix":7},"sk":{"a":0,"k":0,"ix":4},"sa":{"a":0,"k":0,"ix":5},"nm":"Transform"}],"nm":"g","np":2,"cix":2,"bm":0,"ix":1,"mn":"ADBE Vector Group","hd":false}],"ip":0,"op":120,"st":0,"bm":0}],"markers":[]}